LICENSE
MANIFEST.in
README
setup.py
fteproxy/VERSION
fteproxy/__init__.py
fteproxy/cli.py
fteproxy/client.py
fteproxy/conf.py
fteproxy/network_io.py
fteproxy/record_layer.py
fteproxy/regex2dfa.py
fteproxy/relay.py
fteproxy/server.py
fteproxy.egg-info/PKG-INFO
fteproxy.egg-info/SOURCES.txt
fteproxy.egg-info/dependency_links.txt
fteproxy.egg-info/entry_points.txt
fteproxy.egg-info/requires.txt
fteproxy.egg-info/top_level.txt
fteproxy/defs/20131224.json
fteproxy/defs/__init__.py
fteproxy/defs/__init__.pyc
fteproxy/tests/__init__.py
fteproxy/tests/test_record_layer.py
fteproxy/tests/test_relay.py