Metadata-Version: 1.0
Name: fteproxy
Version: 0.2.19
Summary: fteproxy
Home-page: https://fteproxy.org/
Author: Kevin P. Dyer
Author-email: kpdyer@gmail.com
License: UNKNOWN
Platform: UNKNOWN
